teco_challenger_lib/__init__.py
teco_challenger_lib/teco-challenger-lib.py
teco_challenger_lib-0.1.1.dist-info/METADATA
teco_challenger_lib-0.1.1.dist-info/WHEEL
teco_challenger_lib-0.1.1.dist-info/RECORD
