Metadata-Version: 2.1
Name: teco-challenger-lib
Version: 0.1.1
Summary: 
Author: Eduardo Pagnone
Author-email: mlopsaa@teco.com.ar
Requires-Python: >=3.7,<4.0
Classifier: Programming Language :: Python :: 3
Classifier: Programming Language :: Python :: 3.7
Classifier: Programming Language :: Python :: 3.8
Classifier: Programming Language :: Python :: 3.9
Classifier: Programming Language :: Python :: 3.10
Classifier: Programming Language :: Python :: 3.11
Requires-Dist: lightgbm (>=3.3.5,<4.0.0)
Requires-Dist: xgboost (>=1.7.5,<2.0.0)
